revolution/lib.py
revolution/main.py
websocket/__init__.py
websocket/_abnf.py
websocket/_app.py
websocket/_cookiejar.py
websocket/_core.py
websocket/_exceptions.py
websocket/_handshake.py
websocket/_http.py
websocket/_logging.py
websocket/_socket.py
websocket/_ssl_compat.py
websocket/_url.py
websocket/_utils.py
websocket/_wsdump.py
revolution.py-5.0.1.4.dist-info/LICENSE
revolution.py-5.0.1.4.dist-info/METADATA
revolution.py-5.0.1.4.dist-info/WHEEL
revolution.py-5.0.1.4.dist-info/top_level.txt
revolution.py-5.0.1.4.dist-info/RECORD
