Metadata-Version: 2.1
Name: revolution.py
Version: 5.0.1.4
Summary: A simple Py package to integrate Revolution's bot API into python.
Home-page: https://revolution-web.repl.co/
Author: JustAnEric
Maintainer: Revolution Corporation
Keywords: revolutionpy,python3,revolution
Requires: requests
License-File: LICENSE
